comuniitaliani/__init__.py
comuniitaliani/comuni.py
comuniitaliani/exceptions.py
comuniitaliani/loader.py
comuniitaliani/database/comuni.csv
comuniitaliani-0.20.1.dist-info/LICENSE
comuniitaliani-0.20.1.dist-info/METADATA
comuniitaliani-0.20.1.dist-info/WHEEL
comuniitaliani-0.20.1.dist-info/top_level.txt
comuniitaliani-0.20.1.dist-info/RECORD
