Metadata-Version: 2.1
Name: comuniitaliani
Version: 0.20.1
Summary: Libreria Python per ottenere informazioni sui comuni italiani aggiornate da file ISTAT
Home-page: https://github.com/cvrboni/comuniitaliani
Author: Andrea Carboni
Author-email: andreacarboni@stepservizi.net
Classifier: Programming Language :: Python :: 3
Classifier: License :: OSI Approved :: MIT License
Classifier: Operating System :: OS Independent
Requires-Python: >=3.6
License-File: LICENSE
Requires-Dist: pandas >=1.0.0
Requires-Dist: requests >=2.0.0
